session_cli-1.5.0.dist-info/licenses/LICENSE
session_controller/__init__.py
session_controller/cdp.py
session_controller/cli.py
session_controller/config.py
session_controller/constants.py
session_controller/database.py
session_controller/exceptions.py
session_controller/py.typed
session_controller/repl.py
session_controller/user_config.py
session_cli-1.5.0.dist-info/METADATA
session_cli-1.5.0.dist-info/WHEEL
session_cli-1.5.0.dist-info/entry_points.txt
session_cli-1.5.0.dist-info/top_level.txt
session_cli-1.5.0.dist-info/RECORD
