Metadata-Version: 2.4
Name: session-cli
Version: 1.5.0
Summary: Python CLI tool and library for programmatic control of Session Desktop
Author-email: Aman Verasia <verasiaaman3@gmail.com>
Maintainer-email: Aman Verasia <verasiaaman3@gmail.com>
License-Expression: MIT
Project-URL: Homepage, https://github.com/amanverasia/session-cli
Project-URL: Documentation, https://github.com/amanverasia/session-cli#readme
Project-URL: Repository, https://github.com/amanverasia/session-cli
Project-URL: Bug Reports, https://github.com/amanverasia/session-cli/issues
Project-URL: Source, https://github.com/amanverasia/session-cli
Keywords: session,messenger,desktop,cli,cdp,sqlcipher,privacy,encryption
Classifier: Development Status :: 4 - Beta
Classifier: Intended Audience :: Developers
Classifier: Intended Audience :: End Users/Desktop
Classifier: Topic :: Communications :: Chat
Classifier: Topic :: Security :: Cryptography
Classifier: Programming Language :: Python :: 3
Classifier: Programming Language :: Python :: 3.10
Classifier: Programming Language :: Python :: 3.11
Classifier: Programming Language :: Python :: 3.12
Classifier: Programming Language :: Python :: 3.13
Classifier: Operating System :: MacOS
Classifier: Operating System :: POSIX :: Linux
Classifier: Environment :: Console
Classifier: Typing :: Typed
Requires-Python: >=3.10
License-File: LICENSE
Requires-Dist: sqlcipher3>=0.5.0
Requires-Dist: pynacl>=1.5.0
Requires-Dist: websocket-client>=1.0.0
Requires-Dist: pyaes>=1.6.0
Requires-Dist: pyyaml>=6.0.0
Provides-Extra: dev
Requires-Dist: pytest>=7.0.0; extra == "dev"
Requires-Dist: pytest-cov>=4.0.0; extra == "dev"
Requires-Dist: black>=23.0.0; extra == "dev"
Requires-Dist: flake8>=6.0.0; extra == "dev"
Requires-Dist: mypy>=1.0.0; extra == "dev"
Requires-Dist: pre-commit>=3.6.0; extra == "dev"
Dynamic: license-file
